{"paths": {"admin/js/vendor/select2/i18n/pt.js": "admin/js/vendor/select2/i18n/pt.33b4a3b44d43.js", "admin/js/vendor/select2/i18n/hsb.js": "admin/js/vendor/select2/i18n/hsb.fa3b55265efe.js", "admin/js/vendor/select2/i18n/vi.js": "admin/js/vendor/select2/i18n/vi.097a5b75b3e1.js", "admin/js/vendor/select2/i18n/lv.js": "admin/js/vendor/select2/i18n/lv.08e62128eac1.js", "admin/js/vendor/select2/i18n/gl.js": "admin/js/vendor/select2/i18n/gl.d99b1fedaa86.js", "admin/js/vendor/select2/i18n/pl.js": "admin/js/vendor/select2/i18n/pl.6031b4f16452.js", "admin/js/vendor/select2/i18n/el.js": "admin/js/vendor/select2/i18n/el.27097f071856.js", "admin/js/vendor/select2/i18n/dsb.js": "admin/js/vendor/select2/i18n/dsb.56372c92d2f1.js", "admin/js/vendor/select2/i18n/et.js": "admin/js/vendor/select2/i18n/et.2b96fd98289d.js", "admin/js/vendor/select2/i18n/is.js": "admin/js/vendor/select2/i18n/is.3ddd9a6a97e9.js", "admin/js/vendor/select2/i18n/sl.js": "admin/js/vendor/select2/i18n/sl.131a78bc0752.js", "admin/js/vendor/select2/i18n/ko.js": "admin/js/vendor/select2/i18n/ko.e7be6c20e673.js", "admin/js/vendor/select2/i18n/hr.js": "admin/js/vendor/select2/i18n/hr.a2b092cc1147.js", "admin/js/vendor/select2/i18n/ms.js": "admin/js/vendor/select2/i18n/ms.4ba82c9a51ce.js", "admin/js/vendor/select2/i18n/fi.js": "admin/js/vendor/select2/i18n/fi.614ec42aa9ba.js", "admin/js/vendor/select2/i18n/th.js": "admin/js/vendor/select2/i18n/th.f38c20b0221b.js", "admin/js/vendor/select2/i18n/ru.js": "admin/js/vendor/select2/i18n/ru.934aa95f5b5f.js", "admin/js/vendor/select2/i18n/eu.js": "admin/js/vendor/select2/i18n/eu.adfe5c97b72c.js", "admin/js/vendor/select2/i18n/mk.js": "admin/js/vendor/select2/i18n/mk.dabbb9087130.js", "admin/js/vendor/select2/i18n/sq.js": "admin/js/vendor/select2/i18n/sq.5636b60d29c9.js", "admin/js/vendor/select2/i18n/ja.js": "admin/js/vendor/select2/i18n/ja.170ae885d74f.js", "admin/js/vendor/select2/i18n/ka.js": "admin/js/vendor/select2/i18n/ka.2083264a54f0.js", "admin/js/vendor/select2/i18n/he.js": "admin/js/vendor/select2/i18n/he.e420ff6cd3ed.js", "admin/js/vendor/select2/i18n/bg.js": "admin/js/vendor/select2/i18n/bg.39b8be30d4f0.js", "admin/js/vendor/select2/i18n/hy.js": "admin/js/vendor/select2/i18n/hy.c7babaeef5a6.js", "admin/js/vendor/select2/i18n/sr-Cyrl.js": "admin/js/vendor/select2/i18n/sr-Cyrl.f254bb8c4c7c.js", "admin/js/vendor/select2/i18n/ne.js": "admin/js/vendor/select2/i18n/ne.3d79fd3f08db.js", "admin/js/vendor/select2/i18n/af.js": "admin/js/vendor/select2/i18n/af.4f6fcd73488c.js", "admin/js/vendor/select2/i18n/id.js": "admin/js/vendor/select2/i18n/id.04debded514d.js", "admin/js/vendor/select2/i18n/az.js": "admin/js/vendor/select2/i18n/az.270c257daf81.js", "admin/js/vendor/select2/i18n/ca.js": "admin/js/vendor/select2/i18n/ca.a166b745933a.js", "admin/js/vendor/select2/i18n/nb.js": "admin/js/vendor/select2/i18n/nb.da2fce143f27.js", "admin/js/vendor/select2/i18n/zh-CN.js": "admin/js/vendor/select2/i18n/zh-CN.2cff662ec5f9.js", "admin/js/vendor/select2/i18n/zh-TW.js": "admin/js/vendor/select2/i18n/zh-TW.04554a227c2b.js", "admin/js/vendor/select2/i18n/pt-BR.js": "admin/js/vendor/select2/i18n/pt-BR.e1b294433e7f.js", "admin/js/vendor/select2/i18n/da.js": "admin/js/vendor/select2/i18n/da.766346afe4dd.js", "admin/js/vendor/select2/i18n/fa.js": "admin/js/vendor/select2/i18n/fa.3b5bd1961cfd.js", "admin/js/vendor/select2/i18n/de.js": "admin/js/vendor/select2/i18n/de.8a1c222b0204.js", "admin/js/vendor/select2/i18n/en.js": "admin/js/vendor/select2/i18n/en.cf932ba09a98.js", "admin/js/vendor/select2/i18n/bs.js": "admin/js/vendor/select2/i18n/bs.91624382358e.js", "admin/js/vendor/select2/i18n/tk.js": "admin/js/vendor/select2/i18n/tk.7c572a68c78f.js", "admin/js/vendor/select2/i18n/sv.js": "admin/js/vendor/select2/i18n/sv.7a9c2f71e777.js", "admin/js/vendor/select2/i18n/hi.js": "admin/js/vendor/select2/i18n/hi.70640d41628f.js", "admin/js/vendor/select2/i18n/uk.js": "admin/js/vendor/select2/i18n/uk.8cede7f4803c.js", "admin/js/vendor/select2/i18n/cs.js": "admin/js/vendor/select2/i18n/cs.4f43e8e7d33a.js", "admin/js/vendor/select2/i18n/km.js": "admin/js/vendor/select2/i18n/km.c23089cb06ca.js", "admin/js/vendor/select2/i18n/fr.js": "admin/js/vendor/select2/i18n/fr.05e0542fcfe6.js", "admin/js/vendor/select2/i18n/nl.js": "admin/js/vendor/select2/i18n/nl.997868a37ed8.js", "admin/js/vendor/select2/i18n/sr.js": "admin/js/vendor/select2/i18n/sr.5ed85a48f483.js", "admin/js/vendor/select2/i18n/hu.js": "admin/js/vendor/select2/i18n/hu.6ec6039cb8a3.js", "admin/js/vendor/select2/i18n/lt.js": "admin/js/vendor/select2/i18n/lt.23c7ce903300.js", "admin/js/vendor/select2/i18n/ar.js": "admin/js/vendor/select2/i18n/ar.65aa8e36bf5d.js", "admin/js/vendor/select2/i18n/sk.js": "admin/js/vendor/select2/i18n/sk.33d02cef8d11.js", "admin/js/vendor/select2/i18n/it.js": "admin/js/vendor/select2/i18n/it.be4fe8d365b5.js", "admin/js/vendor/select2/i18n/es.js": "admin/js/vendor/select2/i18n/es.66dbc2652fb1.js", "admin/js/vendor/select2/i18n/bn.js": "admin/js/vendor/select2/i18n/bn.6d42b4dd5665.js", "admin/js/vendor/select2/i18n/ro.js": "admin/js/vendor/select2/i18n/ro.f75cb460ec3b.js", "admin/js/vendor/select2/i18n/ps.js": "admin/js/vendor/select2/i18n/ps.38dfa47af9e0.js", "admin/js/vendor/select2/i18n/tr.js": "admin/js/vendor/select2/i18n/tr.b5a0643d1545.js", "admin/css/vendor/select2/select2.min.css": "admin/css/vendor/select2/select2.min.9f54e6414f87.css", "admin/css/vendor/select2/LICENSE-SELECT2.md": "admin/css/vendor/select2/LICENSE-SELECT2.f94142512c91.md", "admin/css/vendor/select2/select2.css": "admin/css/vendor/select2/select2.a2194c262648.css", "admin/js/vendor/jquery/jquery.min.js": "admin/js/vendor/jquery/jquery.min.dc5e7f18c8d3.js", "admin/js/vendor/jquery/LICENSE.txt": "admin/js/vendor/jquery/LICENSE.75308107741f.txt", "admin/js/vendor/jquery/jquery.js": "admin/js/vendor/jquery/jquery.23c7c5d2d131.js", "admin/js/vendor/xregexp/xregexp.min.js": "admin/js/vendor/xregexp/xregexp.min.b0439563a5d3.js", "admin/js/vendor/xregexp/xregexp.js": "admin/js/vendor/xregexp/xregexp.efda034b9537.js", "admin/js/vendor/xregexp/LICENSE.txt": "admin/js/vendor/xregexp/LICENSE.bf79e414957a.txt", "admin/js/vendor/select2/LICENSE.md": "admin/js/vendor/select2/LICENSE.f94142512c91.md", "admin/js/vendor/select2/select2.full.min.js": "admin/js/vendor/select2/select2.full.min.fcd7500d8e13.js", "admin/js/vendor/select2/select2.full.js": "admin/js/vendor/select2/select2.full.c2afdeda3058.js", "admin/js/admin/RelatedObjectLookups.js": "admin/js/admin/RelatedObjectLookups.d7e023e6523b.js", "admin/js/admin/DateTimeShortcuts.js": "admin/js/admin/DateTimeShortcuts.29d0b1965c07.js", "admin/img/gis/move_vertex_on.svg": "admin/img/gis/move_vertex_on.0047eba25b67.svg", "admin/img/gis/move_vertex_off.svg": "admin/img/gis/move_vertex_off.7a23bf31ef8a.svg", "rest_framework/docs/css/highlight.css": "rest_framework/docs/css/highlight.e0e4d973c6d7.css", "rest_framework/docs/css/base.css": "rest_framework/docs/css/base.3208b6cc4466.css", "rest_framework/docs/css/jquery.json-view.min.css": "rest_framework/docs/css/jquery.json-view.min.a2e6beeb6710.css", "rest_framework/docs/js/highlight.pack.js": "rest_framework/docs/js/highlight.pack.479b5f21dcba.js", "rest_framework/docs/js/api.js": "rest_framework/docs/js/api.c9743eab7a4f.js", "rest_framework/docs/js/jquery.json-view.min.js": "rest_framework/docs/js/jquery.json-view.min.b7c2d6981377.js", "rest_framework/docs/img/favicon.ico": "rest_framework/docs/img/favicon.5195b4d0f3eb.ico", "rest_framework/docs/img/grid.png": "rest_framework/docs/img/grid.a4b938cf382b.png", "admin/css/widgets.css": "admin/css/widgets.b12c020d05e0.css", "admin/css/login.css": "admin/css/login.d2a477e04949.css", "admin/css/dashboard.css": "admin/css/dashboard.be83f13e4369.css", "admin/css/nav_sidebar.css": "admin/css/nav_sidebar.59831780a474.css", "admin/css/responsive.css": "admin/css/responsive.0ed741a014cf.css", "admin/css/autocomplete.css": "admin/css/autocomplete.781713f30664.css", "admin/css/responsive_rtl.css": "admin/css/responsive_rtl.e13ae754cceb.css", "admin/css/forms.css": "admin/css/forms.6230fc2a74ac.css", "admin/css/fonts.css": "admin/css/fonts.168bab448fee.css", "admin/css/rtl.css": "admin/css/rtl.775b89eb85cb.css", "admin/css/base.css": "admin/css/base.efb520c4bb7c.css", "admin/css/changelists.css": "admin/css/changelists.403ad0c24fa6.css", "admin/js/urlify.js": "admin/js/urlify.3cabcb7a9073.js", "admin/js/inlines.min.js": "admin/js/inlines.min.599e296e4c24.js", "admin/js/core.js": "admin/js/core.fae39a43def0.js", "admin/js/collapse.js": "admin/js/collapse.f84e7410290f.js", "admin/js/actions.js": "admin/js/actions.9fe89b71cbba.js", "admin/js/prepopulate.js": "admin/js/prepopulate.bd2361dfd64d.js", "admin/js/cancel.js": "admin/js/cancel.50e7573ea4a7.js", "admin/js/nav_sidebar.js": "admin/js/nav_sidebar.7605597ddf52.js", "admin/js/autocomplete.js": "admin/js/autocomplete.618a7ebf39d8.js", "admin/js/inlines.js": "admin/js/inlines.7596b7fd289e.js", "admin/js/change_form.js": "admin/js/change_form.9d8ca4f96b75.js", "admin/js/SelectFilter2.js": "admin/js/SelectFilter2.d250dcb52a9a.js", "admin/js/jquery.init.js": "admin/js/jquery.init.b7781a0897fc.js", "admin/js/popup_response.js": "admin/js/popup_response.c6cc78ea5551.js", "admin/js/SelectBox.js": "admin/js/SelectBox.46d59670a7a7.js", "admin/js/actions.min.js": "admin/js/actions.min.5f3040a29159.js", "admin/js/calendar.js": "admin/js/calendar.b4dcf6f850fe.js", "admin/js/prepopulate.min.js": "admin/js/prepopulate.min.5f7f80162256.js", "admin/js/collapse.min.js": "admin/js/collapse.min.10ac29832e2c.js", "admin/js/prepopulate_init.js": "admin/js/prepopulate_init.e056047b7a7e.js", "admin/img/search.svg": "admin/img/search.7cf54ff789c6.svg", "admin/img/icon-calendar.svg": "admin/img/icon-calendar.ac7aea671bea.svg", "admin/img/icon-clock.svg": "admin/img/icon-clock.e1d4dfac3f2b.svg", "admin/img/icon-no.svg": "admin/img/icon-no.439e821418cd.svg", "admin/img/tooltag-add.svg": "admin/img/tooltag-add.e59d620a9742.svg", "admin/img/inline-delete.svg": "admin/img/inline-delete.fec1b761f254.svg", "admin/img/LICENSE": "admin/img/LICENSE.2c54f4e1ca1c", "admin/img/icon-changelink.svg": "admin/img/icon-changelink.18d2fd706348.svg", "admin/img/icon-unknown.svg": "admin/img/icon-unknown.a18cb4398978.svg", "admin/img/sorting-icons.svg": "admin/img/sorting-icons.3a097b59f104.svg", "admin/img/icon-viewlink.svg": "admin/img/icon-viewlink.41eb31f7826e.svg", "admin/img/icon-yes.svg": "admin/img/icon-yes.d2f9f035226a.svg", "admin/img/icon-addlink.svg": "admin/img/icon-addlink.d519b3bab011.svg", "admin/img/icon-unknown-alt.svg": "admin/img/icon-unknown-alt.81536e128bb6.svg", "admin/img/icon-deletelink.svg": "admin/img/icon-deletelink.564ef9dc3854.svg", "admin/img/README.txt": "admin/img/README.a70711a38d87.txt", "admin/img/selector-icons.svg": "admin/img/selector-icons.b4555096cea2.svg", "admin/img/calendar-icons.svg": "admin/img/calendar-icons.39b290681a8b.svg", "admin/img/tooltag-arrowright.svg": "admin/img/tooltag-arrowright.bbfb788a849e.svg", "admin/img/icon-alert.svg": "admin/img/icon-alert.034cc7d8a67f.svg", "admin/fonts/Roboto-Light-webfont.woff": "admin/fonts/Roboto-Light-webfont.c73eb1ceba33.woff", "admin/fonts/Roboto-Bold-webfont.woff": "admin/fonts/Roboto-Bold-webfont.50d75e48e0a3.woff", "admin/fonts/Roboto-Regular-webfont.woff": "admin/fonts/Roboto-Regular-webfont.35b07eb2f871.woff", "admin/fonts/README.txt": "admin/fonts/README.ab99e6b541ea.txt", "admin/fonts/LICENSE.txt": "admin/fonts/LICENSE.d273d63619c9.txt", "rest_framework/css/bootstrap.min.css": "rest_framework/css/bootstrap.min.77017a69879a.css", "rest_framework/css/prettify.css": "rest_framework/css/prettify.a987f72342ee.css", "rest_framework/css/default.css": "rest_framework/css/default.8d5591a6aabc.css", "rest_framework/css/font-awesome-4.0.3.css": "rest_framework/css/font-awesome-4.0.3.c1e1ea213abf.css", "rest_framework/css/bootstrap-tweaks.css": "rest_framework/css/bootstrap-tweaks.46ed116b0edd.css", "rest_framework/css/bootstrap-theme.min.css": "rest_framework/css/bootstrap-theme.min.66b84a04375e.css", "rest_framework/js/ajax-form.js": "rest_framework/js/ajax-form.0ea6e6052ab5.js", "rest_framework/js/prettify-min.js": "rest_framework/js/prettify-min.709bfcc456c6.js", "rest_framework/js/csrf.js": "rest_framework/js/csrf.969930007329.js", "rest_framework/js/jquery-3.5.1.min.js": "rest_framework/js/jquery-3.5.1.min.dc5e7f18c8d3.js", "rest_framework/js/bootstrap.min.js": "rest_framework/js/bootstrap.min.2f34b630ffe3.js", "rest_framework/js/default.js": "rest_framework/js/default.5b08897dbdc3.js", "rest_framework/js/coreapi-0.1.1.js": "rest_framework/js/coreapi-0.1.1.8851fb9336c9.js", "rest_framework/img/grid.png": "rest_framework/img/grid.a4b938cf382b.png", "rest_framework/img/glyphicons-halflings.png": "rest_framework/img/glyphicons-halflings.90233c9067e9.png", "rest_framework/img/glyphicons-halflings-white.png": "rest_framework/img/glyphicons-halflings-white.9bbc6e960299.png", "rest_framework/fonts/fontawesome-webfont.svg": "rest_framework/fonts/fontawesome-webfont.83e37a11f9d7.svg", "rest_framework/fonts/glyphicons-halflings-regular.woff": "rest_framework/fonts/glyphicons-halflings-regular.fa2772327f55.woff", "rest_framework/fonts/glyphicons-halflings-regular.eot": "rest_framework/fonts/glyphicons-halflings-regular.f4769f9bdb74.eot", "rest_framework/fonts/glyphicons-halflings-regular.woff2": "rest_framework/fonts/glyphicons-halflings-regular.448c34a56d69.woff2", "rest_framework/fonts/glyphicons-halflings-regular.ttf": "rest_framework/fonts/glyphicons-halflings-regular.e18bbf611f2a.ttf", "rest_framework/fonts/fontawesome-webfont.ttf": "rest_framework/fonts/fontawesome-webfont.dcb26c7239d8.ttf", "rest_framework/fonts/fontawesome-webfont.woff": "rest_framework/fonts/fontawesome-webfont.3293616ec0c6.woff", "rest_framework/fonts/glyphicons-halflings-regular.svg": "rest_framework/fonts/glyphicons-halflings-regular.08eda92397ae.svg", "rest_framework/fonts/fontawesome-webfont.eot": "rest_framework/fonts/fontawesome-webfont.8b27bc96115c.eot", "css/21.938c68d3.chunk.css.map": "css/21.938c68d3.chunk.css.49ed45990746.map", "css/main.92c87c97.chunk.css": "css/main.92c87c97.chunk.e2cf8bc54294.css", "css/4.c3386583.chunk.css.map": "css/4.c3386583.chunk.css.414a4fd23215.map", "css/main.92c87c97.chunk.css.map": "css/main.92c87c97.chunk.css.dd4e6bcd725d.map", "css/3.2f54a71c.chunk.css.map": "css/3.2f54a71c.chunk.css.af85b61f8321.map", "css/16.a4e07747.chunk.css.map": "css/16.a4e07747.chunk.css.fc5e738ecaf6.map", "css/18.938c68d3.chunk.css.map": "css/18.938c68d3.chunk.css.0b3c614bc3f8.map", "css/3.2f54a71c.chunk.css": "css/3.2f54a71c.chunk.85a1f248f850.css", "css/23.4b8c302d.chunk.css": "css/23.4b8c302d.chunk.0a31567d4347.css", "css/23.4b8c302d.chunk.css.map": "css/23.4b8c302d.chunk.css.d45d48cd3c04.map", "css/14.624ecb17.chunk.css": "css/14.624ecb17.chunk.46f777ceb61e.css", "css/16.a4e07747.chunk.css": "css/16.a4e07747.chunk.c05e0fed1d10.css", "css/24.4b8c302d.chunk.css.map": "css/24.4b8c302d.chunk.css.5896f6ff4596.map", "css/18.938c68d3.chunk.css": "css/18.938c68d3.chunk.e9f696e4242c.css", "css/14.624ecb17.chunk.css.map": "css/14.624ecb17.chunk.css.e1f68fef0c7a.map", "css/17.c504227a.chunk.css.map": "css/17.c504227a.chunk.css.0c5ec6ffbd2a.map", "css/21.938c68d3.chunk.css": "css/21.938c68d3.chunk.84f006771a1c.css", "css/24.4b8c302d.chunk.css": "css/24.4b8c302d.chunk.e7615347d84e.css", "css/20.624ecb17.chunk.css.map": "css/20.624ecb17.chunk.css.0d7c1d514bbf.map", "css/10.85feb332.chunk.css": "css/10.85feb332.chunk.d720203b8ae5.css", "css/20.624ecb17.chunk.css": "css/20.624ecb17.chunk.19b0451e2142.css", "css/17.c504227a.chunk.css": "css/17.c504227a.chunk.5c8e94bcf73c.css", "css/4.c3386583.chunk.css": "css/4.c3386583.chunk.f15ba7252839.css", "css/10.85feb332.chunk.css.map": "css/10.85feb332.chunk.css.3f2dbc1f23d8.map", "js/14.801733ef.chunk.js": "js/14.801733ef.chunk.f1283edad88b.js", "js/0.935afb3f.chunk.js": "js/0.935afb3f.chunk.4658df3383f2.js", "js/11.bc0e9215.chunk.js.LICENSE.txt": "js/11.bc0e9215.chunk.js.LICENSE.3a8c57d68448.txt", "js/9.db0a3341.chunk.js.map": "js/9.db0a3341.chunk.js.36c69dab277d.map", "js/main.d5b64856.chunk.js.map": "js/main.d5b64856.chunk.js.21373f3d619b.map", "js/22.e85ac235.chunk.js": "js/22.e85ac235.chunk.48ef35390bd4.js", "js/1.7c83d0ef.chunk.js": "js/1.7c83d0ef.chunk.cc63214ab45d.js", "js/22.e85ac235.chunk.js.map": "js/22.e85ac235.chunk.js.adb39a152624.map", "js/24.c919baac.chunk.js": "js/24.c919baac.chunk.3cb62bb38784.js", "js/15.669ae86f.chunk.js": "js/15.669ae86f.chunk.a23efd8be252.js", "js/17.b556bcf8.chunk.js": "js/17.b556bcf8.chunk.e16524f4f7c6.js", "js/21.89155cba.chunk.js": "js/21.89155cba.chunk.c964afe193a6.js", "js/25.1eb788d3.chunk.js": "js/25.1eb788d3.chunk.b70189424ef0.js", "js/4.921b98ae.chunk.js.map": "js/4.921b98ae.chunk.js.62574aff6f14.map", "js/16.7960dbad.chunk.js": "js/16.7960dbad.chunk.00eef87e652b.js", "js/6.47aa946f.chunk.js.map": "js/6.47aa946f.chunk.js.c5c122447296.map", "js/5.04d17374.chunk.js.map": "js/5.04d17374.chunk.js.fd694e5e72bd.map", "js/16.7960dbad.chunk.js.map": "js/16.7960dbad.chunk.js.31ae74d9e808.map", "js/1.7c83d0ef.chunk.js.map": "js/1.7c83d0ef.chunk.js.dd7c19140df1.map", "js/24.c919baac.chunk.js.map": "js/24.c919baac.chunk.js.4139dceede99.map", "js/4.921b98ae.chunk.js.LICENSE.txt": "js/4.921b98ae.chunk.js.LICENSE.6b169a63ebd2.txt", "js/17.b556bcf8.chunk.js.map": "js/17.b556bcf8.chunk.js.8be63d182d11.map", "js/13.d3cf476f.chunk.js.map": "js/13.d3cf476f.chunk.js.8f708f7089fc.map", "js/6.47aa946f.chunk.js": "js/6.47aa946f.chunk.23451dceb430.js", "js/21.89155cba.chunk.js.map": "js/21.89155cba.chunk.js.c6a51afb9aec.map", "js/3.83adade6.chunk.js.LICENSE.txt": "js/3.83adade6.chunk.js.LICENSE.4aa4a4e6658e.txt", "js/15.669ae86f.chunk.js.map": "js/15.669ae86f.chunk.js.8cae0f6788fc.map", "js/9.db0a3341.chunk.js": "js/9.db0a3341.chunk.b13e69f93a24.js", "js/14.801733ef.chunk.js.map": "js/14.801733ef.chunk.js.62bde0479f55.map", "js/3.83adade6.chunk.js.map": "js/3.83adade6.chunk.js.38338d583ca6.map", "js/runtime-main.0da0fb94.js.map": "js/runtime-main.0da0fb94.js.6b6358e4ed12.map", "js/10.8c8c53bd.chunk.js.map": "js/10.8c8c53bd.chunk.js.7c22580595f0.map", "js/13.d3cf476f.chunk.js": "js/13.d3cf476f.chunk.8b944f99e4a5.js", "js/12.6968e4b7.chunk.js.map": "js/12.6968e4b7.chunk.js.9a0bba562adc.map", "js/25.1eb788d3.chunk.js.map": "js/25.1eb788d3.chunk.js.2532802feda5.map", "js/20.c1387398.chunk.js.map": "js/20.c1387398.chunk.js.74f6c1e61493.map", "js/20.c1387398.chunk.js": "js/20.c1387398.chunk.46ea5ec09075.js", "js/11.bc0e9215.chunk.js.map": "js/11.bc0e9215.chunk.js.93519e350a53.map", "js/10.8c8c53bd.chunk.js": "js/10.8c8c53bd.chunk.dea1fcd3f1d2.js", "js/0.935afb3f.chunk.js.map": "js/0.935afb3f.chunk.js.20965da83b4c.map", "js/19.8ee8b8c4.chunk.js": "js/19.8ee8b8c4.chunk.9a0f1097144b.js", "js/main.d5b64856.chunk.js": "js/main.d5b64856.chunk.db20a6d41ef3.js", "js/18.39a61351.chunk.js.map": "js/18.39a61351.chunk.js.028f662b2064.map", "js/23.1a1e03e0.chunk.js.map": "js/23.1a1e03e0.chunk.js.624c197560d3.map", "js/12.6968e4b7.chunk.js": "js/12.6968e4b7.chunk.c2fbb392ddad.js", "js/4.921b98ae.chunk.js": "js/4.921b98ae.chunk.939d33b11b21.js", "js/3.83adade6.chunk.js": "js/3.83adade6.chunk.81b59346942c.js", "js/runtime-main.0da0fb94.js": "js/runtime-main.0da0fb94.d5d7da7de178.js", "js/5.04d17374.chunk.js": "js/5.04d17374.chunk.089c7c9313c7.js", "js/19.8ee8b8c4.chunk.js.map": "js/19.8ee8b8c4.chunk.js.0dc1c65fde50.map", "js/18.39a61351.chunk.js": "js/18.39a61351.chunk.d61f9c41b89b.js", "js/23.1a1e03e0.chunk.js": "js/23.1a1e03e0.chunk.9b6c5aa8607e.js", "js/9.db0a3341.chunk.js.LICENSE.txt": "js/9.db0a3341.chunk.js.LICENSE.3f1e2eba7c81.txt", "js/2.f999553f.chunk.js.map": "js/2.f999553f.chunk.js.86e5d9d244be.map", "js/11.bc0e9215.chunk.js": "js/11.bc0e9215.chunk.d5c8ab826d91.js", "js/2.f999553f.chunk.js": "js/2.f999553f.chunk.37fcdc469b0e.js", "js/5.04d17374.chunk.js.LICENSE.txt": "js/5.04d17374.chunk.js.LICENSE.681de766a6a7.txt", "media/graphic-3.32e0e0cb.png": "media/graphic-3.32e0e0cb.32e0e0cbbff3.png", "media/4.abc79dc5.png": "media/4.abc79dc5.abc79dc5f14b.png", "media/ipad-pro.df7d3430.png": "media/ipad-pro.df7d3430.df7d34303f0e.png", "media/updatescreen3.f3bc472d.png": "media/updatescreen3.f3bc472d.f3bc472d187d.png", "media/updatescreen1.faa2d825.png": "media/updatescreen1.faa2d825.faa2d82550d4.png", "media/homepod.e3172634.png": "media/homepod.e3172634.e31726349717.png", "media/macbook-pro.e723c891.png": "media/macbook-pro.e723c891.e723c891248a.png", "media/feather.931c9e74.eot": "media/feather.931c9e74.931c9e74d0b2.eot", "media/jbl-speaker.66807511.png": "media/jbl-speaker.66807511.66807511376b.png", "media/openstreet.d2be4840.png": "media/openstreet.d2be4840.d2be48400947.png", "media/kb-article.034f99d6.jpg": "media/kb-article.034f99d6.034f99d6b318.jpg", "media/logo-white.d2be4840.png": "media/logo-white.d2be4840.d2be48400947.png", "media/graphic-4.0112e680.png": "media/graphic-4.0112e680.0112e6802d36.png", "media/banner-texture.bbd8b16f.png": "media/banner-texture.bbd8b16f.bbd8b16f6fed.png", "media/feather.3d2fa2e5.woff": "media/feather.3d2fa2e5.3d2fa2e54400.woff", "media/process-1.bf1eec09.svg": "media/process-1.bf1eec09.bf1eec0914f7.svg", "media/process-3.527de7a9.svg": "media/process-3.527de7a9.527de7a9522c.svg", "media/openstreet-meth.e0be2991.pdf": "media/openstreet-meth.e0be2991.e0be29919237.pdf", "media/map.40ffdb36.png": "media/map.40ffdb36.40ffdb360205.png", "media/login.fd58a052.png": "media/login.fd58a052.fd58a052054c.png", "media/business.e5fb830a.svg": "media/business.e5fb830a.e5fb830a772f.svg", "media/feather.b23df4db.svg": "media/feather.b23df4db.b23df4db71a2.svg", "media/library.d561dd58.svg": "media/library.d561dd58.d561dd58da69.svg", "media/vuesax-login-bg.eb4e894d.jpg": "media/vuesax-login-bg.eb4e894d.eb4e894d949e.jpg", "media/graphic-5.e6415499.png": "media/graphic-5.e6415499.e641549914a0.png", "media/banner-image2.1c8d3bd4.png": "media/banner-image2.1c8d3bd4.1c8d3bd4eb40.png", "media/updatescreen2.dab5e2cd.png": "media/updatescreen2.dab5e2cd.dab5e2cdab9a.png", "media/10.b1a428ff.png": "media/10.b1a428ff.b1a428ff98a2.png", "media/process-2.cacbed52.svg": "media/process-2.cacbed52.cacbed52ff11.svg", "media/canon-camera.1d0e6cb0.jpg": "media/canon-camera.1d0e6cb0.1d0e6cb08396.jpg", "media/apple-watch.c51a5f8c.png": "media/apple-watch.c51a5f8c.c51a5f8c4671.png", "media/dash-bg.afcfdf67.png": "media/dash-bg.afcfdf67.afcfdf677648.png", "media/graphic-1.58c221eb.png": "media/graphic-1.58c221eb.58c221eb6346.png", "media/iphone-x.ff1daa9e.png": "media/iphone-x.ff1daa9e.ff1daa9ec97c.png", "media/logo.22031607.png": "media/logo.22031607.22031607732d.png", "media/2.456f2534.png": "media/2.456f2534.456f25349e81.png", "media/1.c537e387.png": "media/1.c537e387.c537e38778a8.png", "media/feather.6a750f01.ttf": "media/feather.6a750f01.6a750f0119ba.ttf", "media/knowledge-base-cover.254ae2df.jpg": "media/knowledge-base-cover.254ae2df.254ae2dfebb5.jpg", "media/graphic-6.4df5e78b.png": "media/graphic-6.4df5e78b.4df5e78b8bcc.png", "media/sony-75class-tv.9f82c4b3.jpg": "media/sony-75class-tv.9f82c4b3.9f82c4b3494f.jpg", "media/footer-bg.61e61976.png": "media/footer-bg.61e61976.61e61976e8a4.png", "media/magic-mouse.3cf7a781.png": "media/magic-mouse.3cf7a781.3cf7a781374f.png", "media/area_chart.16d63f5e.svg": "media/area_chart.16d63f5e.16d63f5ed70c.svg", "media/register.23d1bae7.jpg": "media/register.23d1bae7.23d1bae7ef4c.jpg", "media/7.0b1bc286.png": "media/7.0b1bc286.0b1bc286923c.png", "media/graphic-2.6dd844b4.png": "media/graphic-2.6dd844b4.6dd844b4e1c2.png"}, "version": "1.0"}